intake_nested_yaml_catalog/__init__.py
intake_nested_yaml_catalog/nested_yaml_catalog.py
intake_nested_yaml_catalog/docs/genindex.html
intake_nested_yaml_catalog/docs/index.html
intake_nested_yaml_catalog/docs/objects.inv
intake_nested_yaml_catalog/docs/search.html
intake_nested_yaml_catalog/docs/searchindex.js
intake_nested_yaml_catalog/docs/.doctrees/environment.pickle
intake_nested_yaml_catalog/docs/.doctrees/index.doctree
intake_nested_yaml_catalog/docs/_sources/index.rst.txt
intake_nested_yaml_catalog/docs/_static/basic.css
intake_nested_yaml_catalog/docs/_static/doctools.js
intake_nested_yaml_catalog/docs/_static/documentation_options.js
intake_nested_yaml_catalog/docs/_static/file.png
intake_nested_yaml_catalog/docs/_static/jquery-3.4.1.js
intake_nested_yaml_catalog/docs/_static/jquery.js
intake_nested_yaml_catalog/docs/_static/language_data.js
intake_nested_yaml_catalog/docs/_static/minus.png
intake_nested_yaml_catalog/docs/_static/plus.png
intake_nested_yaml_catalog/docs/_static/pygments.css
intake_nested_yaml_catalog/docs/_static/searchtools.js
intake_nested_yaml_catalog/docs/_static/underscore-1.3.1.js
intake_nested_yaml_catalog/docs/_static/underscore.js
intake_nested_yaml_catalog/docs/_static/css/badge_only.css
intake_nested_yaml_catalog/docs/_static/css/theme.css
intake_nested_yaml_catalog/docs/_static/fonts/Inconsolata-Bold.ttf
intake_nested_yaml_catalog/docs/_static/fonts/Inconsolata-Regular.ttf
intake_nested_yaml_catalog/docs/_static/fonts/Inconsolata.ttf
intake_nested_yaml_catalog/docs/_static/fonts/Lato-Bold.ttf
intake_nested_yaml_catalog/docs/_static/fonts/Lato-Regular.ttf
intake_nested_yaml_catalog/docs/_static/fonts/RobotoSlab-Bold.ttf
intake_nested_yaml_catalog/docs/_static/fonts/RobotoSlab-Regular.ttf
intake_nested_yaml_catalog/docs/_static/fonts/fontawesome-webfont.eot
intake_nested_yaml_catalog/docs/_static/fonts/fontawesome-webfont.svg
intake_nested_yaml_catalog/docs/_static/fonts/fontawesome-webfont.ttf
intake_nested_yaml_catalog-0.1.0.dist-info/LICENSE
intake_nested_yaml_catalog-0.1.0.dist-info/METADATA
intake_nested_yaml_catalog-0.1.0.dist-info/WHEEL
intake_nested_yaml_catalog-0.1.0.dist-info/entry_points.txt
intake_nested_yaml_catalog-0.1.0.dist-info/top_level.txt
intake_nested_yaml_catalog-0.1.0.dist-info/RECORD
