Metadata-Version: 2.1
Name: intake-nested-yaml-catalog
Version: 0.1.0
Summary: Intake single YAML hierarchical catalog.
Home-page: UNKNOWN
Author: Zillow AI Platform
Author-email: 
License: UNKNOWN
Platform: UNKNOWN
Requires-Python: >=3.6
Requires-Dist: vcver
Requires-Dist: intake
Requires-Dist: pandas
Requires-Dist: PyYAML
Requires-Dist: deepmerge
